spatialnc/__init__.py
spatialnc/analysis.py
spatialnc/cli.py
spatialnc/ipw.py
spatialnc/proj.py
spatialnc/tools.py
spatialnc/topo.py
spatialnc/utilities.py
spatialnc-0.4.1.dist-info/LICENSE
spatialnc-0.4.1.dist-info/METADATA
spatialnc-0.4.1.dist-info/WHEEL
spatialnc-0.4.1.dist-info/entry_points.txt
spatialnc-0.4.1.dist-info/top_level.txt
spatialnc-0.4.1.dist-info/RECORD
