Metadata-Version: 1.1
Name: spatialnc
Version: 0.4.1
Summary: Python library for handling spatial data in netcdfs specifically for modeling with SMRF/AWSM
Home-page: https://github.com/USDA-ARS-NWRC/spatialnc
Author: USDA ARS NWRC
Author-email: snow@ars.usda.gov
License: MIT license
Keywords: spatialnc
Platform: UNKNOWN
Classifier: Development Status :: 2 - Pre-Alpha
Classifier: Intended Audience :: Developers
Classifier: License :: CC0 1.0 Universal (CC0 1.0) Public Domain Dedication
Classifier: Natural Language :: English
Classifier: Programming Language :: Python :: 3.5
Classifier: Programming Language :: Python :: 3.6
Classifier: Programming Language :: Python :: 3.7
Classifier: Programming Language :: Python :: 3.8
